mozvpn/__init__.py
mozvpn/cli.py
mozvpn/mozvpn.py
mozvpn/mozvpn_gui.py
mozvpn/wireguard.py
mozvpn-0.2.1.dist-info/AUTHORS.rst
mozvpn-0.2.1.dist-info/LICENSE
mozvpn-0.2.1.dist-info/METADATA
mozvpn-0.2.1.dist-info/WHEEL
mozvpn-0.2.1.dist-info/entry_points.txt
mozvpn-0.2.1.dist-info/top_level.txt
mozvpn-0.2.1.dist-info/RECORD
