Metadata-Version: 2.1
Name: mozvpn
Version: 0.2.1
Summary: Tools and GUI for MozillaVPN.
Home-page: https://github.com/ralhei/mozvpn
Author: Ralph Heinkel
Author-email: rh@ralph-heinkel.com
License: GNU General Public License v3
Keywords: mozvpn
Platform: UNKNOWN
Classifier: Development Status :: 2 - Pre-Alpha
Classifier: Intended Audience :: Developers
Classifier: License :: OSI Approved :: GNU General Public License v3 (GPLv3)
Classifier: Natural Language :: English
Classifier: Programming Language :: Python :: 3
Classifier: Programming Language :: Python :: 3.6
Classifier: Programming Language :: Python :: 3.7
Classifier: Programming Language :: Python :: 3.8
Classifier: Programming Language :: Python :: 3.9
Requires-Python: >=3.6
Requires-Dist: Click (>=7.0)
Requires-Dist: requests
Requires-Dist: PyQt6
